piewordle/__init__.py
piewordle/__main__.py
piewordle/wordle.py
piewordle/util/data.py
piewordle/util/dictionary.py
piewordle/util/thread.py
piewordle-0.1.1.dist-info/entry_points.txt
piewordle-0.1.1.dist-info/LICENSE
piewordle-0.1.1.dist-info/WHEEL
piewordle-0.1.1.dist-info/METADATA
piewordle-0.1.1.dist-info/RECORD
