Metadata-Version: 2.1
Name: piewordle
Version: 0.1.1
Summary: A Recreation of Wordle in Python.
Keywords: games,wordle,word games,english,german,CUI,crossplatform,python,terminal
Author-email: "Silas A. Kraume" <silas.kraume1552@gmail.com>
Requires-Python: >=3.7
Classifier: License :: OSI Approved :: MIT License
Classifier: Programming Language :: Python
Classifier: Programming Language :: Python :: 3
Classifier: Programming Language :: Python :: 3.7
Classifier: Programming Language :: Python :: 3.8
Classifier: Programming Language :: Python :: 3.9
Classifier: Programming Language :: Python :: 3.10
Classifier: Programming Language :: Python :: 3.11
Classifier: Programming Language :: Python :: 3.12
Classifier: Programming Language :: Python :: Implementation :: PyPy
Classifier: Environment :: Console
Classifier: Operating System :: OS Independent
Classifier: Topic :: Terminals
Project-URL: Download, https://github.com/SilenZcience/PieWordle/tarball/master
Project-URL: Github, https://github.com/SilenZcience/PieWordle
Project-URL: Tracker, https://github.com/SilenZcience/PieWordle/issues
